README.rst
setup.py
scripts/tios-add_guest
scripts/tios-add_user
scripts/tios-collect
scripts/tios-config
scripts/tios-config_admin
scripts/tios-cp
scripts/tios-download
scripts/tios-info
scripts/tios-list_users
scripts/tios-ls
scripts/tios-passwd
scripts/tios-remove_user
scripts/tios-reset
scripts/tios-restart
scripts/tios-rm
scripts/tios-run
scripts/tios-stop
scripts/tios-submit
test/__init__.py
test/test_dummy_connection.py
test/test_gromacs_imd_sim.py
test/test_gromacs_utilities.py
test/test_mongo_connection.py
test/test_namd_imd_sim.py
test/test_namd_utilities.py
test/test_tios_data.py
test/test_tios_namd_transmitter.py
test/test_tios_receiver.py
test/test_tios_transmitter.py
test/test_utilities.py
test/test_utilities_gromacs_2018.py
test/test_utilities_namd2_212.py
tios/__init__.py
tios/_version.py
tios/admin.py
tios/communication.py
tios/environments.py
tios/graphics.py
tios/gromacs_utilities.py
tios/imd.py
tios/imd_sim.py
tios/namd_utilities.py
tios/receiver.py
tios/transmitter.py
tios/utilities.py
tios/web.py
tios.egg-info/PKG-INFO
tios.egg-info/SOURCES.txt
tios.egg-info/dependency_links.txt
tios.egg-info/not-zip-safe
tios.egg-info/requires.txt
tios.egg-info/top_level.txt