Metadata-Version: 1.1
Name: tios
Version: 1.0.2
Summary: The internet of things, for MD simulations.
Home-page: https://bitbucket.org/claughton/tios/wiki/Home
Author: Charlie Laughton
Author-email: charles.laughton@nottingham.ac.uk
License: BSD license.
Download-URL: https://bitbucket.org/claughton/tios
Platform: UNKNOWN
Classifier: Development Status :: 3 - Alpha
Classifier: Intended Audience :: Science/Research
Classifier: Environment :: Console
Classifier: License :: OSI Approved :: BSD License
Classifier: Programming Language :: Python
Classifier: Programming Language :: Python :: 2
Classifier: Programming Language :: Python :: 2.7
Classifier: Programming Language :: Python :: 3
Classifier: Programming Language :: Python :: 3.4
Classifier: Programming Language :: Python :: 3.5
Classifier: Topic :: Scientific/Engineering
Classifier: Operating System :: MacOS :: MacOS X
Classifier: Operating System :: POSIX
Classifier: Operating System :: Unix
